cmd.py
setup.py
micropython_cmd.egg-info/PKG-INFO
micropython_cmd.egg-info/SOURCES.txt
micropython_cmd.egg-info/dependency_links.txt
micropython_cmd.egg-info/top_level.txt