Metadata-Version: 1.0
Name: micropython-cmd
Version: 0.0.1
Summary: CPython cmd module ported to MicroPython
Home-page: https://github.com/micropython/micropython/issues/405
Author: MicroPython Developers
Author-email: micro-python@googlegroups.com
License: Python
Platform: UNKNOWN
